dodoo/__init__.py
dodoo/cli.py
dodoo/commands.py
dodoo/console.py
dodoo/env.py
dodoo/options.py
dodoo-2.0.0rc8.dist-info/LICENSE
dodoo-2.0.0rc8.dist-info/METADATA
dodoo-2.0.0rc8.dist-info/WHEEL
dodoo-2.0.0rc8.dist-info/entry_points.txt
dodoo-2.0.0rc8.dist-info/top_level.txt
dodoo-2.0.0rc8.dist-info/RECORD
