Metadata-Version: 2.1
Name: dodoo
Version: 2.0.0rc8
Summary: Beautiful, robust and extensible Odoo server API extension suite for DevOps.
Home-page: http://github.com/xoe-labs/dodoo
Author: XOE Corp. SAS
Author-email: info@xoe.solutions
License: LGPLv3+
Platform: UNKNOWN
Classifier: Development Status :: 5 - Production/Stable
Classifier: Intended Audience :: Developers
Classifier: License :: OSI Approved :: GNU Lesser General Public License v3 or later (LGPLv3+)
Classifier: Programming Language :: Python :: 2.7
Classifier: Programming Language :: Python :: 3.5
Classifier: Programming Language :: Python :: 3.6
Classifier: Framework :: Odoo
Requires-Dist: click
Requires-Dist: click-plugins
